<?xml version='1.0' encoding='UTF-8'?>
<types:mule xmlns:types="http://www.mulesoft.org/schema/mule/types">
  <types:catalog>
    <types:type name="numero" format="java">
      <types:shape format="raml"><![CDATA[#%RAML 1.0 DataType
type: integer]]></types:shape>
    </types:type>
  </types:catalog>
  <types:enrichment select="#10386176-12ae-4d04-9798-126f80c4e4f3">
    <types:processor-declaration>
      <types:output-event>
        <types:message>
          <types:payload type="numero"/>
        </types:message>
      </types:output-event>
    </types:processor-declaration>
  </types:enrichment>
</types:mule>